guilded_webhook/__init__.py
guilded_webhook/embed.py
guilded_webhook/exceptions.py
guilded_webhook/file.py
guilded_webhook-0.3.1.dist-info/LICENSE
guilded_webhook-0.3.1.dist-info/METADATA
guilded_webhook-0.3.1.dist-info/WHEEL
guilded_webhook-0.3.1.dist-info/top_level.txt
guilded_webhook-0.3.1.dist-info/RECORD
