Metadata-Version: 2.1
Name: guilded-webhook
Version: 0.3.1
Summary: guilded-webhook is a basic wrapper for guilded's webhooks.
Home-page: https://github.com/anytarseir67/guilded-webhook
Author: anytarseir67
License: GPLv3
Platform: UNKNOWN
License-File: LICENSE
Requires-Dist: requests
Requires-Dist: aiohttp
